proco_pkg/__init__.py
proco_pkg/udf.py
proco_pkg_kamalneel81-0.0.1.dist-info/LICENSE.txt
proco_pkg_kamalneel81-0.0.1.dist-info/METADATA
proco_pkg_kamalneel81-0.0.1.dist-info/WHEEL
proco_pkg_kamalneel81-0.0.1.dist-info/top_level.txt
proco_pkg_kamalneel81-0.0.1.dist-info/RECORD
