Metadata-Version: 2.1
Name: proco-pkg-kamalneel81
Version: 0.0.1
Summary: proco package
Home-page: https://github.com/pypa/sampleproject
Author: Kamal, Neel
Author-email: kamalneel81@gmail.com
License: UNKNOWN
Platform: UNKNOWN
Classifier: Programming Language :: Python :: 3
Classifier: License :: OSI Approved :: MIT License
Classifier: Operating System :: OS Independent
Requires-Python: >=3.6
